{"chunk_definitions":[{"row":12,"row_count":1,"visible":true,"expansion_state":0,"options":{"engine":"r","label":"unnamed-chunk-1","dev":"png"},"document_id":"548BBEFA","chunk_id":"crii7qsctpofl","chunk_label":"unnamed-chunk-1"},{"row":17,"row_count":1,"visible":true,"expansion_state":0,"options":{"engine":"r","label":"unnamed-chunk-2","dev":"png"},"document_id":"548BBEFA","chunk_id":"c6bf04r0tl9h5","chunk_label":"unnamed-chunk-2"},{"row":37,"row_count":1,"visible":true,"expansion_state":0,"options":{"engine":"r","label":"unnamed-chunk-12","dev":"png"},"document_id":"548BBEFA","chunk_id":"cbakpe83zds18","chunk_label":"unnamed-chunk-3"},{"row":52,"row_count":1,"visible":true,"expansion_state":0,"options":{"engine":"r","label":"unnamed-chunk-4","dev":"png"},"document_id":"548BBEFA","chunk_id":"crpvpufh2xnbb","chunk_label":"unnamed-chunk-4"},{"row":62,"row_count":1,"visible":true,"expansion_state":0,"options":{"engine":"r","label":"unnamed-chunk-11","dev":"png"},"document_id":"548BBEFA","chunk_id":"csdzhx4zmfba6","chunk_label":"unnamed-chunk-5"},{"row":87,"row_count":1,"visible":true,"expansion_state":0,"options":{"engine":"r","label":"unnamed-chunk-13","dev":"png"},"document_id":"548BBEFA","chunk_id":"chwvhexdi4pmn","chunk_label":"unnamed-chunk-6"},{"row":108,"row_count":1,"visible":true,"expansion_state":0,"options":{"engine":"r","label":"unnamed-chunk-25","dev":"png"},"document_id":"548BBEFA","chunk_id":"c2gq5ciurormn","chunk_label":"unnamed-chunk-7"}],"doc_write_time":1713297343}